_kalk/__init__.py
_kalk/binary_ops.py
_kalk/unary_ops.py
kalk-0.19.0.dist-info/WHEEL
kalk-0.19.0.dist-info/entry_points.txt
kalk-0.19.0.dist-info/METADATA
kalk-0.19.0.dist-info/RECORD
