Metadata-Version: 2.3
Name: kalk
Version: 0.19.0
Summary: a simple cli RPN calculator written in Python
Keywords: calculator,kalkulator,cli,RPN
Author: 5j9
Author-email: 5j9 <5j9@users.noreply.github.com>
License: GNU General Public License v3 (GPLv3)
Classifier: Intended Audience :: End Users/Desktop
Classifier: License :: OSI Approved :: GNU General Public License v3 or later (GPLv3+)
Classifier: Programming Language :: Python :: 3.9
Classifier: Topic :: Scientific/Engineering
Requires-Dist: regex
Requires-Dist: pyperclip
Requires-Dist: jdatetime>=5.2.0
Requires-Dist: pyreadline3>=3.5.4 ; sys_platform == 'win32'
Requires-Python: >=3.9
Project-URL: Homepage, https://github.com/5j9/kalk
